project/pd0/design/code/reg_rst.sv
/*
 * Module: reg_rst
 *
 * Description: A DWIDTH register implementation with
 * synchronous reset. Input is registered at the rising
 * edge of the clock.
 *
 * Inputs:
 * 1) clk
 * 2) rst signal
 * 3) DWIDTH input in_i
 *
 * Outputs:
 * 1) DWIDTH output out_o
 *
 */
module reg_rst #(
    parameter int DWIDTH = 32)(
    input logic clk,
    input logic rst,
    input logic [DWIDTH-1:0] in_i,
    output logic [DWIDTH-1:0] out_o
);
    /*
     * Process definitions to be filled by
     * student below...
     */

    always_ff @(posedge clk) begin
        if (rst)
            out_o <= '0;      // synchronous reset
        else
            out_o <= in_i;    // input captured on the rising edge of the clock
    end

endmodule: reg_rst

project/pd0/design/code/alu.sv
/*
 * Module: alu
 *
 * Description: A simple ALU module that does addition, subtraction,
 * logical or and logical and operation. The operations are
 * combinational circuits.
 *
 * Inputs:
 * 1) DWIDTH-wide input op1_i
 * 2) DWIDTH-wide input op2_i
 * 3) 2-bit selection signal sel_i
 * (refer constants_pkg.sv for the selection signals)
 *
 * Outputs:
 * 1) DWIDTH-wide result res_o
 * 2) 1-bit signal that is asserted if result is zero zero_o
 * 3) 1-bit signal that is asserted if result is negative neg_o
 */

// Declare the enumerations in a package
import constants_pkg::*;

module alu #(
    parameter int DWIDTH = 8)(
        input logic [1:0] sel_i,
        input logic [DWIDTH-1:0] op1_i,
        input logic [DWIDTH-1:0] op2_i,
        output logic [DWIDTH-1:0] res_o,
        output logic zero_o,
        output logic neg_o
    );

    /*
     * Process definitions to be filled by
     * student below...
     */
    
     logic [DWIDTH-1:0] result;

     always_comb begin
        case (aluSel_e'(sel_i))
            ADD: result = op1_i + op2_i;
            SUB: result = op1_i - op2_i;
            AND: result = op1_i & op2_i;
            OR: result = op1_i | op2_i;
            default: result = '0;
        endcase
    end

    assign res_o = result;
    assign zero_o = (res_o == '0);
    assign neg_o = res_o[DWIDTH-1];

endmodule: alu

project/pd0/design/code/three_stage_pipeline.sv
/*
 * Module: three_stage_pipeline
 *
 * A 3-stage pipeline (TSP) where the first stage performs an addition of two
 * operands (op1_i, op2_i) and registers the output, and the second stage computes
 * the difference between the output from the first stage and op1_i and registers the
 * output. This means that the output (res_o) must be available two cycles after the
 * corresponding inputs have been observed on the rising clock edge
 *
 * Visually, the circuit should look like this:
 *               <---         Stage 1           --->
 *                                                        <---         Stage 2           --->
 *                                                                                               <--    Stage 3    -->
 *                                    |------------------>|                    |
 * -- op1_i -->|                    | --> |         |     |                    |-->|         |   |                    |
 *             | pipeline registers |     | ALU add | --> | pipeline registers |   | ALU sub |-->| pipeline register  | -- res_o -->
 * -- op2_i -->|                    | --> |         |     |                    |-->|         |   |                    |
 *
 * Inputs:
 * 1) 1-bit clock signal
 * 2) 1-bit wide synchronous reset
 * 3) DWIDTH-wide input op1_i
 * 4) DWIDTH-wide input op2_i
 *
 * Outputs:
 * 1) DWIDTH-wide result res_o
 */

import constants_pkg::*;


module three_stage_pipeline #(
parameter int DWIDTH = 8)(
        input logic clk,
        input logic rst,
        input logic [DWIDTH-1:0] op1_i,
        input logic [DWIDTH-1:0] op2_i,
        output logic [DWIDTH-1:0] res_o
    );

    /*
     * Process definitions to be filled by
     * student below...
     * [HINT] Instantiate the alu and reg_rst modules
     * and set up the necessary connections
     *
     */

    // Stage 1: ALU add

    logic [DWIDTH-1:0] add_res; // results of the ALU add
    logic z_add, n_add;

    alu #(.DWIDTH(DWIDTH)) unit_alu_add (
        .sel_i  (ADD),
        .op1_i  (op1_i),
        .op2_i  (op2_i),
        .res_o  (add_res),
        .zero_o (z_add),
        .neg_o  (n_add)
    );

    // Stage 2: pipeline registers + ALU sub
    // Register the results from ALU add
    // Register op1_i to align with the registered ALU add results
    
    logic [DWIDTH-1:0] add_res_reg;
    logic [DWIDTH-1:0] op1_fwd_reg;

    // Register ADD result
    reg_rst #(.DWIDTH(DWIDTH)) unit_add_res_reg (
        .clk   (clk),
        .rst   (rst),
        .in_i  (add_res),
        .out_o (add_res_reg)
    );

    // Forward aligned op1 register
    reg_rst #(.DWIDTH(DWIDTH)) unit_op1_fwd_reg (
        .clk   (clk),
        .rst   (rst),
        .in_i  (op1_i),
        .out_o (op1_fwd_reg)
    );

    logic [DWIDTH-1:0] sub_res;
    logic z_sub, n_sub;

    alu #(.DWIDTH(DWIDTH)) unit_alu_sub (
        .sel_i  (SUB),
        .op1_i  (add_res_reg), 
        .op2_i  (op1_fwd_reg),
        .res_o  (sub_res),
        .zero_o (z_sub),
        .neg_o  (n_sub)
    );

    // Stage 3: Final output register
    // Registers the SUB result so res_o appears two cycles after inputs
    
    reg_rst #(.DWIDTH(DWIDTH)) unit_res_reg (
        .clk   (clk),
        .rst   (rst),
        .in_i  (sub_res),
        .out_o (res_o)
    );

endmodule: three_stage_pipeline

project/pd0/design/code/pd0_testbench.sv
`timescale 1ns/1ps

// Simple testbench for ALU, register, and 3-stage pipeline
// Just runs some basic tests and dumps waveforms

import constants_pkg::*;

module pd0_testbench;

  // Basic stuff
  parameter DWIDTH = 8;
  
  logic clk = 0;
  logic rst;

  // ALU signals
  logic [DWIDTH-1:0] alu_a, alu_b, alu_result;
  logic [1:0] alu_op;
  logic zero_flag, neg_flag;

  // Register signals  
  logic [DWIDTH-1:0] reg_data_in, reg_data_out;

  // Pipeline signals
  logic [DWIDTH-1:0] pipe_in1, pipe_in2, pipe_out;

  // Instantiate the modules
  alu #(.DWIDTH(DWIDTH)) my_alu (
    .sel_i(alu_op),
    .op1_i(alu_a),
    .op2_i(alu_b), 
    .res_o(alu_result),
    .zero_o(zero_flag),
    .neg_o(neg_flag)
  );

  reg_rst #(.DWIDTH(DWIDTH)) my_reg (
    .clk(clk),
    .rst(rst),
    .in_i(reg_data_in),
    .out_o(reg_data_out)
  );

  three_stage_pipeline #(.DWIDTH(DWIDTH)) my_pipeline (
    .clk(clk),
    .rst(rst), 
    .op1_i(pipe_in1),
    .op2_i(pipe_in2),
    .res_o(pipe_out)
  );

  // Clock - just toggle every 5ns
  always #5 clk = ~clk;

  // Dump waveforms
  initial begin
    $dumpfile("waves.vcd");
    $dumpvars;
  end

  // Main test
  initial begin
    // Start with reset
    rst = 1;
    alu_a = 0; alu_b = 0; alu_op = ADD;
    reg_data_in = 0;
    pipe_in1 = 0; pipe_in2 = 0;
    
    // Wait a few clock cycles then release reset
    repeat(3) @(posedge clk);
    rst = 0;
    @(posedge clk);
    
    $display("Starting tests...");
    
    // Test the ALU with some simple operations
    $display("\n--- Testing ALU ---");
    alu_a = 15; alu_b = 10; alu_op = ADD;
    #1;  // Small delay for combinational logic to settle
    $display("ADD: %0d + %0d = %0d (zero=%b, neg=%b)", alu_a, alu_b, alu_result, zero_flag, neg_flag);
    
    alu_a = 20; alu_b = 5; alu_op = SUB; 
    #1;
    $display("SUB: %0d - %0d = %0d (zero=%b, neg=%b)", alu_a, alu_b, alu_result, zero_flag, neg_flag);
    
    alu_a = 8'hAA; alu_b = 8'h55; alu_op = AND;
    #1; 
    $display("AND: 0x%h & 0x%h = 0x%h", alu_a, alu_b, alu_result);
    
    alu_a = 8'hA0; alu_b = 8'h05; alu_op = OR;
    #1;
    $display("OR:  0x%h | 0x%h = 0x%h", alu_a, alu_b, alu_result);

    // Test the register - just store and read back some values
    $display("\n--- Testing Register ---");
    
    // Check initial state after reset
    $display("Initial register value: %0d", reg_data_out);
    
    // Set input, wait for clock, then check output
    reg_data_in = 42;
    @(posedge clk);
    #1; // Small delay after clock edge
    $display("After storing 42: %0d", reg_data_out);
    
    reg_data_in = 123;
    @(posedge clk);
    #1; 
    $display("After storing 123: %0d", reg_data_out);
    
    // Test reset functionality - reset should take effect immediately on clock edge
    reg_data_in = 99; // Set some value
    rst = 1;
    @(posedge clk);
    #1;
    $display("After reset: %0d (should be 0)", reg_data_out);
    rst = 0;
    @(posedge clk);

    // Test the pipeline - looks like it has 3 cycle latency based on the output
    $display("\n--- Testing Pipeline ---");
    
    // Apply first input
    pipe_in1 = 100; pipe_in2 = 25;
    $display("Cycle 1 - Input: op1=%0d, op2=%0d", pipe_in1, pipe_in2);
    @(posedge clk);
    
    // Apply second input  
    pipe_in1 = 50; pipe_in2 = 30; 
    $display("Cycle 2 - Input: op1=%0d, op2=%0d, Output: %0d", pipe_in1, pipe_in2, pipe_out);
    @(posedge clk);
    
    // Third cycle 
    pipe_in1 = 75; pipe_in2 = 10;
    $display("Cycle 3 - Input: op1=%0d, op2=%0d, Output: %0d", pipe_in1, pipe_in2, pipe_out);
    @(posedge clk);
    
    // Fourth cycle - first result should appear here (3 cycle latency)
    pipe_in1 = 0; pipe_in2 = 0;
    $display("Cycle 4 - Output: %0d (should be 25 from cycle 1)", pipe_out);
    @(posedge clk);
    
    // Fifth cycle - second result appears
    $display("Cycle 5 - Output: %0d (should be 30 from cycle 2)", pipe_out);
    @(posedge clk);
    
    // Sixth cycle - third result appears
    $display("Cycle 6 - Output: %0d (should be 10 from cycle 3)", pipe_out);
    @(posedge clk);
    
    // Seventh cycle - should see 0 now
    $display("Cycle 7 - Output: %0d (should be 0)", pipe_out);
    
    // All done
    $display("\nTests finished!");
    $finish;
  end

endmodule

project/pd0/design/code/waves.vcd
$date
	Fri Sep 26 22:57:25 2025
$end
$version
	ModelSim Version 2020.1
$end
$timescale
	1ps
$end

$scope module pd0_testbench $end
$var parameter 32 ! DWIDTH $end
$var reg 1 " clk $end
$var reg 1 # rst $end
$var reg 8 $ alu_a [7:0] $end
$var reg 8 % alu_b [7:0] $end
$var reg 8 & alu_result [7:0] $end
$var reg 2 ' alu_op [1:0] $end
$var reg 1 ( zero_flag $end
$var reg 1 ) neg_flag $end
$var reg 8 * reg_data_in [7:0] $end
$var reg 8 + reg_data_out [7:0] $end
$var reg 8 , pipe_in1 [7:0] $end
$var reg 8 - pipe_in2 [7:0] $end
$var reg 8 . pipe_out [7:0] $end

$scope module my_alu $end
$var parameter 32 / DWIDTH $end
$var wire 1 0 sel_i [1] $end
$var wire 1 1 sel_i [0] $end
$var wire 1 2 op1_i [7] $end
$var wire 1 3 op1_i [6] $end
$var wire 1 4 op1_i [5] $end
$var wire 1 5 op1_i [4] $end
$var wire 1 6 op1_i [3] $end
$var wire 1 7 op1_i [2] $end
$var wire 1 8 op1_i [1] $end
$var wire 1 9 op1_i [0] $end
$var wire 1 : op2_i [7] $end
$var wire 1 ; op2_i [6] $end
$var wire 1 < op2_i [5] $end
$var wire 1 = op2_i [4] $end
$var wire 1 > op2_i [3] $end
$var wire 1 ? op2_i [2] $end
$var wire 1 @ op2_i [1] $end
$var wire 1 A op2_i [0] $end
$var reg 8 B res_o [7:0] $end
$var reg 1 C zero_o $end
$var reg 1 D neg_o $end
$var reg 8 E result [7:0] $end
$upscope $end

$scope module my_reg $end
$var parameter 32 F DWIDTH $end
$var wire 1 G clk $end
$var wire 1 H rst $end
$var wire 1 I in_i [7] $end
$var wire 1 J in_i [6] $end
$var wire 1 K in_i [5] $end
$var wire 1 L in_i [4] $end
$var wire 1 M in_i [3] $end
$var wire 1 N in_i [2] $end
$var wire 1 O in_i [1] $end
$var wire 1 P in_i [0] $end
$var reg 8 Q out_o [7:0] $end
$upscope $end

$scope module my_pipeline $end
$var parameter 32 R DWIDTH $end
$var wire 1 S clk $end
$var wire 1 T rst $end
$var wire 1 U op1_i [7] $end
$var wire 1 V op1_i [6] $end
$var wire 1 W op1_i [5] $end
$var wire 1 X op1_i [4] $end
$var wire 1 Y op1_i [3] $end
$var wire 1 Z op1_i [2] $end
$var wire 1 [ op1_i [1] $end
$var wire 1 \ op1_i [0] $end
$var wire 1 ] op2_i [7] $end
$var wire 1 ^ op2_i [6] $end
$var wire 1 _ op2_i [5] $end
$var wire 1 ` op2_i [4] $end
$var wire 1 a op2_i [3] $end
$var wire 1 b op2_i [2] $end
$var wire 1 c op2_i [1] $end
$var wire 1 d op2_i [0] $end
$var reg 8 e res_o [7:0] $end
$var reg 8 f add_res [7:0] $end
$var reg 1 g z_add $end
$var reg 1 h n_add $end
$var reg 8 i add_res_reg [7:0] $end
$var reg 8 j op1_fwd_reg [7:0] $end
$var reg 8 k sub_res [7:0] $end
$var reg 1 l z_sub $end
$var reg 1 m n_sub $end

$scope module unit_alu_add $end
$var parameter 32 n DWIDTH $end
$var wire 1 o sel_i [1] $end
$var wire 1 p sel_i [0] $end
$var wire 1 U op1_i [7] $end
$var wire 1 V op1_i [6] $end
$var wire 1 W op1_i [5] $end
$var wire 1 X op1_i [4] $end
$var wire 1 Y op1_i [3] $end
$var wire 1 Z op1_i [2] $end
$var wire 1 [ op1_i [1] $end
$var wire 1 \ op1_i [0] $end
$var wire 1 ] op2_i [7] $end
$var wire 1 ^ op2_i [6] $end
$var wire 1 _ op2_i [5] $end
$var wire 1 ` op2_i [4] $end
$var wire 1 a op2_i [3] $end
$var wire 1 b op2_i [2] $end
$var wire 1 c op2_i [1] $end
$var wire 1 d op2_i [0] $end
$var reg 8 q res_o [7:0] $end
$var reg 1 r zero_o $end
$var reg 1 s neg_o $end
$var reg 8 t result [7:0] $end
$upscope $end

$scope module unit_add_res_reg $end
$var parameter 32 u DWIDTH $end
$var wire 1 S clk $end
$var wire 1 T rst $end
$var wire 1 v in_i [7] $end
$var wire 1 w in_i [6] $end
$var wire 1 x in_i [5] $end
$var wire 1 y in_i [4] $end
$var wire 1 z in_i [3] $end
$var wire 1 { in_i [2] $end
$var wire 1 | in_i [1] $end
$var wire 1 } in_i [0] $end
$var reg 8 ~ out_o [7:0] $end
$upscope $end

$scope module unit_op1_fwd_reg $end
$var parameter 32 !! DWIDTH $end
$var wire 1 S clk $end
$var wire 1 T rst $end
$var wire 1 U in_i [7] $end
$var wire 1 V in_i [6] $end
$var wire 1 W in_i [5] $end
$var wire 1 X in_i [4] $end
$var wire 1 Y in_i [3] $end
$var wire 1 Z in_i [2] $end
$var wire 1 [ in_i [1] $end
$var wire 1 \ in_i [0] $end
$var reg 8 "! out_o [7:0] $end
$upscope $end

$scope module unit_alu_sub $end
$var parameter 32 #! DWIDTH $end
$var wire 1 $! sel_i [1] $end
$var wire 1 %! sel_i [0] $end
$var wire 1 &! op1_i [7] $end
$var wire 1 '! op1_i [6] $end
$var wire 1 (! op1_i [5] $end
$var wire 1 )! op1_i [4] $end
$var wire 1 *! op1_i [3] $end
$var wire 1 +! op1_i [2] $end
$var wire 1 ,! op1_i [1] $end
$var wire 1 -! op1_i [0] $end
$var wire 1 .! op2_i [7] $end
$var wire 1 /! op2_i [6] $end
$var wire 1 0! op2_i [5] $end
$var wire 1 1! op2_i [4] $end
$var wire 1 2! op2_i [3] $end
$var wire 1 3! op2_i [2] $end
$var wire 1 4! op2_i [1] $end
$var wire 1 5! op2_i [0] $end
$var reg 8 6! res_o [7:0] $end
$var reg 1 7! zero_o $end
$var reg 1 8! neg_o $end
$var reg 8 9! result [7:0] $end
$upscope $end

$scope module unit_res_reg $end
$var parameter 32 :! DWIDTH $end
$var wire 1 S clk $end
$var wire 1 T rst $end
$var wire 1 ;! in_i [7] $end
$var wire 1 <! in_i [6] $end
$var wire 1 =! in_i [5] $end
$var wire 1 >! in_i [4] $end
$var wire 1 ?! in_i [3] $end
$var wire 1 @! in_i [2] $end
$var wire 1 A! in_i [1] $end
$var wire 1 B! in_i [0] $end
$var reg 8 C! out_o [7:0] $end
$upscope $end
$upscope $end
$upscope $end

$scope begin constants_pkg $end
$upscope $end

$scope begin pd0_testbench_sv_unit $end
$upscope $end

$scope begin std $end
$upscope $end

$scope begin alu_sv_unit $end
$upscope $end

$scope begin three_stage_pipeline_sv_unit $end
$upscope $end
$enddefinitions $end
#0
$dumpvars
0"
1#
b0 $
b0 %
b0 &
b0 '
1(
0)
b0 *
bx +
b0 ,
b0 -
bx .
b0 B
1C
0D
b0 E
bx Q
bx e
b0 f
1g
0h
b0 q
1r
0s
b0 t
bx i
bx j
bx ~
bx "!
bx k
xl
xm
bx 6!
x7!
x8!
bx 9!
bx C!
b1000 !
b1000 /
b1000 F
b1000 R
b1000 n
b1000 u
b1000 !!
b1000 #!
b1000 :!
01
00
09
08
07
06
05
04
03
02
0A
0@
0?
0>
0=
0<
0;
0:
0G
1H
0P
0O
0N
0M
0L
0K
0J
0I
0S
1T
0\
0[
0Z
0Y
0X
0W
0V
0U
0d
0c
0b
0a
0`
0_
0^
0]
0p
0o
0}
0|
0{
0z
0y
0x
0w
0v
1%!
0$!
x-!
x,!
x+!
x*!
x)!
x(!
x'!
x&!
x5!
x4!
x3!
x2!
x1!
x0!
x/!
x.!
xB!
xA!
x@!
x?!
x>!
x=!
x<!
x;!
$end
#5
1"
1S
1G
b0 Q
b0 ~
b0 "!
b0 C!
b0 e
b0 j
b0 i
b0 +
b0 .
0-!
0,!
0+!
0*!
0)!
0(!
0'!
0&!
05!
04!
03!
02!
01!
00!
0/!
0.!
b0 9!
b0 6!
b0 k
17!
08!
0m
1l
0B!
0A!
0@!
0?!
0>!
0=!
0<!
0;!
#10
0"
0S
0G
#15
1"
1S
1G
#20
0"
0S
0G
#25
1"
1S
1G
0#
0T
0H
#30
0"
0S
0G
#35
1"
1S
1G
b1111 $
b1010 %
1@
1>
19
18
17
16
b11001 E
b11001 B
b11001 &
0C
0(
#36
b10100 $
b101 %
b1 '
11
1A
0@
1?
0>
09
08
06
15
b1111 E
b1111 B
b1111 &
#37
b10101010 $
b1010101 %
b10 '
01
10
1=
1;
18
07
16
05
14
12
b0 E
b0 B
b0 &
1C
1(
#38
b10100000 $
b101 %
b11 '
11
0=
0;
08
06
b10100101 E
b10100101 B
b10100101 &
0C
1D
1)
0(
#39
b101010 *
1O
1M
1K
#40
0"
0S
0G
#45
1"
1S
1G
b101010 Q
b101010 +
#46
b1111011 *
1P
1L
1J
#50
0"
0S
0G
#55
1"
1S
1G
b1111011 Q
b1111011 +
#56
b1100011 *
1#
0M
0L
1T
1H
#60
0"
0S
0G
#65
1"
1S
1G
b0 Q
b0 +
#66
0#
0T
0H
#70
0"
0S
0G
#75
1"
1S
1G
b1100100 ,
b11001 -
1d
1a
1`
1Z
1W
1V
b1111101 t
b1111101 q
b1111101 f
0r
0g
1}
1{
1z
1y
1x
1w
b1100011 Q
b1100011 +
#80
0"
0S
0G
#85
1"
1S
1G
b110010 ,
b11110 -
0d
1c
1b
1[
0Z
1X
0V
b1010000 t
b1010000 q
b1010000 f
0}
0{
0z
0x
b1111101 ~
b1100100 "!
b1100100 j
b1111101 i
1-!
1+!
1*!
1)!
1(!
1'!
13!
10!
1/!
b11001 9!
b11001 6!
b11001 k
07!
0l
1B!
1?!
1>!
#90
0"
0S
0G
#95
1"
1S
1G
b1001011 ,
b1010 -
0b
0`
1\
1Y
0X
0W
1V
b1010101 t
b1010101 q
b1010101 f
1}
1{
b1010000 ~
b110010 "!
b11001 C!
b11001 e
b110010 j
b1010000 i
b11001 .
0-!
0+!
0*!
0(!
14!
03!
11!
0/!
b11110 9!
b11110 6!
b11110 k
0B!
1A!
1@!
#100
0"
0S
0G
#105
1"
1S
1G
b0 ,
b0 -
0c
0a
0\
0[
0Y
0V
b0 t
b0 q
b0 f
1r
1g
0}
0{
0y
0w
b1010101 ~
b1001011 "!
b11110 C!
b11110 e
b1001011 j
b1010101 i
b11110 .
1-!
1+!
15!
12!
01!
00!
1/!
b1010 9!
b1010 6!
b1010 k
0@!
0>!
#110
0"
0S
0G
#115
1"
1S
1G
b0 ~
b0 "!
b1010 C!
b1010 e
b0 j
b0 i
b1010 .
0-!
0+!
0)!
0'!
05!
04!
02!
0/!
b0 9!
b0 6!
b0 k
17!
1l
0A!
0?!
#120
0"
0S
0G
#125
1"
1S
1G
b0 C!
b0 e
b0 .
